assert_rewriter/__init__.py
assert_rewriter/compatibility.py
assert_rewriter/core.py
assert_rewriter/samples.py
assert_rewriter/tests.py
assert_rewriter-1.0.dist-info/LICENSE
assert_rewriter-1.0.dist-info/METADATA
assert_rewriter-1.0.dist-info/WHEEL
assert_rewriter-1.0.dist-info/top_level.txt
assert_rewriter-1.0.dist-info/RECORD
