Metadata-Version: 2.1
Name: assert-rewriter
Version: 1.0
Summary: Rewrite function bytecode to support assert introspection.
Home-page: https://github.com/brandon-rhodes/assert_rewriter/
Author: Brandon Rhodes
Author-email: brandon@rhodesmill.org
License: MIT
Platform: UNKNOWN
Classifier: Development Status :: 5 - Production/Stable
Classifier: Intended Audience :: Developers
Classifier: License :: OSI Approved :: MIT License
Classifier: Programming Language :: Python :: 2.7
Classifier: Programming Language :: Python :: 3.7
Classifier: Programming Language :: Python :: 3.8
Classifier: Programming Language :: Python :: 3.9
Classifier: Programming Language :: Python :: 3.10
Classifier: Programming Language :: Python :: 3.11
Classifier: Programming Language :: Python :: 3.12
